crane/__init__.py
crane/admin.py
crane/api_version.py
crane/apps.py
crane/data_migrations.py
crane/delta.py
crane/management/__init__.py
crane/management/commands/__init__.py
crane/management/commands/makeapimigrations.py
crane/management/commands/showapimigrations.py
crane/management/commands/validateapimigrations.py
crane/middleware.py
crane/migrations/__init__.py
crane/migrations_generator.py
crane/models.py
crane/openapi_version.py
crane/path_rewriting.py
crane/templates/crane/versioned_swagger.html
crane/templates/crane/versioned_swagger_cdn.html
crane/tests.py
crane/transformers.py
crane/versioned_api.py
crane/views.py
django_ninja_crane-0.1.9.dist-info/WHEEL
django_ninja_crane-0.1.9.dist-info/METADATA
django_ninja_crane-0.1.9.dist-info/RECORD
