Metadata-Version: 2.3
Name: django-ninja-crane
Version: 0.1.9
Summary: Add versioning and migrations for your Django Ninja API.
Author: Lode Rosseel
Author-email: Lode Rosseel <lode@braced.dev>
Classifier: Development Status :: 4 - Beta
Classifier: License :: OSI Approved :: MIT License
Classifier: Intended Audience :: Developers
Classifier: Operating System :: OS Independent
Classifier: Programming Language :: Python
Classifier: Topic :: Software Development :: Libraries :: Python Modules
Classifier: Typing :: Typed
Classifier: Framework :: Django
Classifier: Framework :: Django :: 6.0
Requires-Dist: django>=6.0
Requires-Dist: django-ninja>=1.5.1
Requires-Python: >=3.12
Project-URL: Repository, https://github.com/lode-braced/django-ninja-crane
Project-URL: Documentation, https://lode-braced.github.io/django-ninja-crane/
